odoo/addons/website_sale_tax_toggle/README.rst
odoo/addons/website_sale_tax_toggle/__init__.py
odoo/addons/website_sale_tax_toggle/__manifest__.py
odoo/addons/website_sale_tax_toggle/controllers/__init__.py
odoo/addons/website_sale_tax_toggle/controllers/main.py
odoo/addons/website_sale_tax_toggle/i18n/ca.po
odoo/addons/website_sale_tax_toggle/i18n/es.po
odoo/addons/website_sale_tax_toggle/i18n/fr.po
odoo/addons/website_sale_tax_toggle/i18n/it.po
odoo/addons/website_sale_tax_toggle/i18n/nl.po
odoo/addons/website_sale_tax_toggle/i18n/website_sale_tax_toggle.pot
odoo/addons/website_sale_tax_toggle/migrations/18.0.1.0.0/pre-migration.py
odoo/addons/website_sale_tax_toggle/models/__init__.py
odoo/addons/website_sale_tax_toggle/models/ir_http.py
odoo/addons/website_sale_tax_toggle/models/product_template.py
odoo/addons/website_sale_tax_toggle/readme/CONFIGURE.md
odoo/addons/website_sale_tax_toggle/readme/CONTRIBUTORS.md
odoo/addons/website_sale_tax_toggle/readme/DESCRIPTION.md
odoo/addons/website_sale_tax_toggle/readme/USAGE.md
odoo/addons/website_sale_tax_toggle/static/description/icon.png
odoo/addons/website_sale_tax_toggle/static/description/index.html
odoo/addons/website_sale_tax_toggle/static/src/js/website_sale_tax_toggle.esm.js
odoo/addons/website_sale_tax_toggle/static/src/js/website_sale_tax_toggle_tour.esm.js
odoo/addons/website_sale_tax_toggle/static/src/scss/website_sale_tax_toggle.scss
odoo/addons/website_sale_tax_toggle/tests/__init__.py
odoo/addons/website_sale_tax_toggle/tests/test_website_sale_tax_toggle.py
odoo/addons/website_sale_tax_toggle/views/templates.xml
odoo_addon_website_sale_tax_toggle-18.0.1.0.0.2.dist-info/METADATA
odoo_addon_website_sale_tax_toggle-18.0.1.0.0.2.dist-info/WHEEL
odoo_addon_website_sale_tax_toggle-18.0.1.0.0.2.dist-info/top_level.txt
odoo_addon_website_sale_tax_toggle-18.0.1.0.0.2.dist-info/RECORD
